setup.py
sample/__init__.py
sample_eddie_lin.egg-info/PKG-INFO
sample_eddie_lin.egg-info/SOURCES.txt
sample_eddie_lin.egg-info/dependency_links.txt
sample_eddie_lin.egg-info/not-zip-safe
sample_eddie_lin.egg-info/top_level.txt