Metadata-Version: 1.0
Name: sample-eddie-lin
Version: 0.5
Summary: Sample Package
Home-page: https://github.com/informetis/sample-package.git
Author: EddieLin
Author-email: UNKNOWN
License: Informetis
Platform: UNKNOWN
